clappia_api_tools/__init__.py
clappia_api_tools/client/__init__.py
clappia_api_tools/client/analytics_client.py
clappia_api_tools/client/app_definition_client.py
clappia_api_tools/client/base_client.py
clappia_api_tools/client/file_management_client.py
clappia_api_tools/client/submission_client.py
clappia_api_tools/client/workflow_definition_client.py
clappia_api_tools/client/workplace_client.py
clappia_api_tools/enums/__init__.py
clappia_api_tools/enums/enums.py
clappia_api_tools/models/__init__.py
clappia_api_tools/models/analytics.py
clappia_api_tools/models/base_model.py
clappia_api_tools/models/definition.py
clappia_api_tools/models/json_serialized.py
clappia_api_tools/models/resapi_output.py
clappia_api_tools/models/sort_field.py
clappia_api_tools/models/static_attachment.py
clappia_api_tools/models/submission.py
clappia_api_tools/models/workflow.py
clappia_api_tools/models/workplace.py
clappia_api_tools/models/request/__init__.py
clappia_api_tools/models/request/analytics.py
clappia_api_tools/models/request/submission.py
clappia_api_tools/models/request/workflow.py
clappia_api_tools/models/request/workplace.py
clappia_api_tools/models/request/app_definition/__init__.py
clappia_api_tools/models/request/app_definition/field.py
clappia_api_tools/models/request/app_definition/metadata.py
clappia_api_tools/models/request/app_definition/page.py
clappia_api_tools/models/request/app_definition/section.py
clappia_api_tools/utils/__init__.py
clappia_api_tools/utils/api_utils.py
clappia_api_tools/utils/file_utils.py
clappia_api_tools/utils/utils.py
clappia_api_tools-2.0.25.dist-info/METADATA
clappia_api_tools-2.0.25.dist-info/WHEEL
clappia_api_tools-2.0.25.dist-info/top_level.txt
clappia_api_tools-2.0.25.dist-info/RECORD
