Metadata-Version: 2.4
Name: clappia-api-tools
Version: 2.0.25
Summary: Python client for Clappia API integration
Author-email: Rishabh Verma <rishabh.v@clappia.com>
License: MIT
Project-URL: Homepage, https://github.com/clappia-dev/clappia-api-tools
Project-URL: Documentation, https://github.com/clappia-dev/clappia-api-tools#readme
Project-URL: Repository, https://github.com/clappia-dev/clappia-api-tools.git
Project-URL: Bug Tracker, https://github.com/clappia-dev/clappia-api-tools/issues
Keywords: clappia,client,mcp,rest-apis,tools,workchat,agents
Classifier: Development Status :: 3 - Alpha
Classifier: Intended Audience :: Developers
Classifier: License :: OSI Approved :: MIT License
Classifier: Operating System :: OS Independent
Classifier: Programming Language :: Python :: 3
Classifier: Programming Language :: Python :: 3.10
Classifier: Programming Language :: Python :: 3.11
Classifier: Programming Language :: Python :: 3.12
Requires-Python: >=3.10
Requires-Dist: requests>=2.31.0
Requires-Dist: python-dotenv>=1.0.0
Requires-Dist: pydantic[email]>=2.0.0
Requires-Dist: typing-extensions>=4.8.0
Requires-Dist: phonenumbers>=9.0.12
Provides-Extra: dev
Requires-Dist: ruff>=0.1.6; extra == "dev"
Requires-Dist: mypy>=1.0.0; extra == "dev"
Requires-Dist: pre-commit>=3.0.0; extra == "dev"
Requires-Dist: bandit>=1.7.5; extra == "dev"
Requires-Dist: safety>=3.6.0; extra == "dev"
Requires-Dist: pip-audit>=2.6.0; extra == "dev"
Requires-Dist: types-requests>=2.31.0; extra == "dev"
Provides-Extra: docs
Requires-Dist: mkdocs>=1.4.0; extra == "docs"
Requires-Dist: mkdocs-material>=9.0.0; extra == "docs"
Requires-Dist: mkdocs-swagger-ui-tag>=0.6.0; extra == "docs"
Provides-Extra: security
Requires-Dist: bandit>=1.7.5; extra == "security"
Requires-Dist: safety>=2.3.0; extra == "security"
Requires-Dist: pip-audit>=2.6.0; extra == "security"
